COPYING
MANIFEST.in
README
courier-pythonfilter.spec
dropmsg
pythonfilter
pythonfilter-modules.conf
pythonfilter-quarantine
pythonfilter.conf
setup.py
courier/__init__.py
courier/authdaemon.py
courier/config.py
courier/control.py
courier/quarantine.py
courier/sendmail.py
courier/xfilter.py
courier_pythonfilter.egg-info/PKG-INFO
courier_pythonfilter.egg-info/SOURCES.txt
courier_pythonfilter.egg-info/dependency_links.txt
courier_pythonfilter.egg-info/top_level.txt
filters/pythonfilter/__init__.py
filters/pythonfilter/add_signature.py
filters/pythonfilter/attachments.py
filters/pythonfilter/auto_whitelist.py
filters/pythonfilter/clamav.py
filters/pythonfilter/comeagain.py
filters/pythonfilter/debug.py
filters/pythonfilter/deliveredto.py
filters/pythonfilter/dialback.py
filters/pythonfilter/greylist.py
filters/pythonfilter/localsenders.py
filters/pythonfilter/log_aliases.py
filters/pythonfilter/noduplicates.py
filters/pythonfilter/noreceivedheaders.py
filters/pythonfilter/nosuccessdsn.py
filters/pythonfilter/privateaddr.py
filters/pythonfilter/quota.py
filters/pythonfilter/ratelimit.py
filters/pythonfilter/ratelimitauth.py
filters/pythonfilter/sentfolder.py
filters/pythonfilter/spamassassin.py
filters/pythonfilter/spfcheck.py
filters/pythonfilter/ttldb.py
filters/pythonfilter/whitelist_auth.py
filters/pythonfilter/whitelist_block.py
filters/pythonfilter/whitelist_dnswl.py
filters/pythonfilter/whitelist_relayclients.py
filters/pythonfilter/whitelist_spf.py
tests/__init__.py
tests/test_config.py
tests/test_control.py
tests/test_moduleconfig.py
tests/test_pythonfilter.py
tests/test_ttldb.py
tests/test_xfilter.py
tests/configfiles/aliases
tests/configfiles/defaultdomain
tests/configfiles/hosteddomains
tests/configfiles/locallowercase
tests/configfiles/locals
tests/configfiles/me
tests/configfiles/pythonfilter-modules.conf
tests/configfiles/smtpaccess
tests/queuefiles/control-duplicate
tests/queuefiles/control-iso-8859-2
tests/queuefiles/control-ldapalias
tests/queuefiles/control-xalias
tests/queuefiles/data-attachment
tests/queuefiles/data-attachments
tests/queuefiles/data-iso-8859-2
tests/queuefiles/data-iso-8859-2.orig
