Metadata-Version: 2.1
Name: courier-pythonfilter
Version: 3.0.6
Summary: Python filtering architecture for the Courier MTA.
Home-page: https://github.com/gordonmessmer/courier-pythonfilter
Author: Gordon Messmer
Author-email: gordon@dragonsdawn.net
License: GPL
License-File: COPYING
